Workbook
Name Discount_Rate: Reference!$C$6
Name Growth_Rate: Inputs!$C$7:$F$7
Name Revenue_Input: Inputs!$C$6:$F$6
Name Tax_Rate: Reference!$C$7

Sheet Cover
B8: FBM Excel Formatting Standard
B10: [Workbook Title]
B12: Prepared by: | C12: Andrew Kim
B13: Department: | C13: Operations FP&A
B14: Date: | C14: 46163
B15: Version: | C15: 1
B16: File location:
B17: Purpose: | C17: Standard FBM workbook template with cell styles, named ranges, and example sheets.
B20: Legend
B21: Cell Style | C21: Example | D21: Use For
B22: FBM Input | C22: 1000 | D22: Hardcoded inputs (blue text)
B23: FBM Formula | C23: 2000 | D23: Calculated formulas (black text)
B24: FBM Link | C24: 3000 | D24: Links from other sheets (green text)
B25: FBM External | C25: 4000 | D25: External file links (red text)
B26: FBM Assumption | C26: 0.1 | D26: Key assumption (yellow fill, blue bold)
B28: Tab Color Coding
B29: Color | C29: Purpose | D29: Example Sheet
B30: Blue | C30: Inputs / data entry | D30: Inputs
B31: Green | C31: Outputs / results / summaries | D31: Output
B32: Gray | C32: Reference / lookup tables | D32: Reference

Sheet Inputs
B2: Inputs
B3: Blue text cells are user-editable. Do not overwrite black formula cells.
B5: Item | C5: FY2026 | D5: FY2027 | E5: FY2028 | F5: FY2029
B6: Revenue ($) | C6: 10000000 | D6: 10500000 | E6: 11025000 | F6: 11576250
B7: Growth rate (%) | C7: 0.05 | D7: 0.05 | E7: 0.05 | F7: 0.05
B8: COGS ($) | C8: 6000000 | D8: 6300000 | E8: 6615000 | F8: 6945750
B9: Headcount (#) | C9: 50 | D9: 52 | E9: 55 | F9: 58

Sheet Calc
B2: Calculations
B5: Metric | C5: FY2026 | D5: FY2027 | E5: FY2028 | F5: FY2029
B6: Revenue | C6: =Inputs!C6 -> 10000000 | D6: =Inputs!D6 -> 10500000 | E6: =Inputs!E6 -> 11025000 | F6: =Inputs!F6 -> 11576250
B7: COGS | C7: =Inputs!C8 -> 6000000 | D7: =Inputs!D8 -> 6300000 | E7: =Inputs!E8 -> 6615000 | F7: =Inputs!F8 -> 6945750
B8: Gross Profit | C8: =C6-C7 -> 4000000 | D8: =D6-D7 -> 4200000 | E8: =E6-E7 -> 4410000 | F8: =F6-F7 -> 4630500
B9: Gross Margin % | C9: =IFERROR(C8/C6,0) -> 0.4 | D9: =IFERROR(D8/D6,0) -> 0.4 | E9: =IFERROR(E8/E6,0) -> 0.4 | F9: =IFERROR(F8/F6,0) -> 0.4

Sheet Output
B2: Output Summary
B5: KPI | C5: FY2026 | D5: FY2027 | E5: FY2028 | F5: FY2029
B6: Revenue | C6: =Calc!C6 -> 10000000 | D6: =Calc!D6 -> 10500000 | E6: =Calc!E6 -> 11025000 | F6: =Calc!F6 -> 11576250
B7: Gross Profit | C7: =Calc!C8 -> 4000000 | D7: =Calc!D8 -> 4200000 | E7: =Calc!E8 -> 4410000 | F7: =Calc!F8 -> 4630500
B8: Gross Margin % | C8: =Calc!C9 -> 0.4 | D8: =Calc!D9 -> 0.4 | E8: =Calc!E9 -> 0.4 | F8: =Calc!F9 -> 0.4
B10: Total Revenue (4Y) | C10: =SUM(C6:F6) -> 43101250

Sheet Reference
B2: Reference / Lookup Tables
B5: Key | C5: Value
B6: Discount rate | C6: 0.1
B7: Tax rate | C7: 0.21
B8: FY start month | C8: 1
B9: Working days/yr | C9: 252
